Metadata-Version: 2.1
Name: py-ztj-aria2rpc
Version: 0.0.4
Summary: python aria2rpc package
Home-page: https://github.com/ztj1993/py-aria2rpc
Author: ZhangTianJie
Author-email: ztj1993@gmail.com
License: MIT License
Keywords: aria2 rpc client
Platform: UNKNOWN
